Metadata-Version: 1.0
Name: fakegit
Version: 0.1
Summary: A great tool to fool yourself and others
Home-page: https://github.com/hanbang-wang/FakeGit
Author: SuperFashi
Author-email: admin@superfashi.com
License: Unlicense
Download-URL: https://github.com/hanbang-wang/FakeGit/tarball/master
Keywords: git,fakegit
Platform: UNKNOWN
Classifier: Development Status :: 5 - Production/Stable
Classifier: License :: Freely Distributable
